quick_in_voice/__init__.py
quick_in_voice/invoice_generator.py
quick_in_voice/utils.py
quick_in_voice-0.1.1.dist-info/LICENSE
quick_in_voice-0.1.1.dist-info/METADATA
quick_in_voice-0.1.1.dist-info/WHEEL
quick_in_voice-0.1.1.dist-info/top_level.txt
quick_in_voice-0.1.1.dist-info/RECORD
