Metadata-Version: 2.2
Name: quick_in_voice
Version: 0.1.1
Summary: A simple automated invoice generation package
Home-page: https://github.com/Nathishwar-prog/Invoicegenerator_module-python
Author: Nathishwar
Author-email: nathishwarc@gmail.com
Classifier: Programming Language :: Python :: 3
Classifier: License :: OSI Approved :: MIT License
Classifier: Operating System :: OS Independent
Requires-Python: >=3.6
License-File: LICENSE
Requires-Dist: fpdf
Requires-Dist: pandas
Requires-Dist: reportlab
Requires-Dist: openpyxl
Dynamic: author
Dynamic: author-email
Dynamic: classifier
Dynamic: description
Dynamic: description-content-type
Dynamic: home-page
Dynamic: requires-dist
Dynamic: requires-python
Dynamic: summary
